{
  "type": "Feature",
  "stac_version": "1.0.0",
  "id": "S3A_SY_2_VG1____20200609T120000_20200610T120000_20200615T121610_CENTRAL_AMERICA___LN2_O_NT_002",
  "properties": {
    "sat:platform_international_designator": "2016-011A",
    "sat:orbit_state": "ascending",
    "sat:absolute_orbit": 22455,
    "sat:relative_orbit": 152,
    "eo:cloud_cover": 9.465587,
    "proj:epsg": 4326,
    "start_datetime": "2020-06-09 12:00:00+00:00",
    "end_datetime": "2020-06-10 12:00:00+00:00",
    "s3:instrument": "SYNERGY",
    "s3:mode": "EO",
    "s3:productType": "SY_2_VG1___",
    "s3:snowOrIcePixels_percentage": 0.066818,
    "s3:landPixels_percentage": 22.527562,
    "providers": [
      {
        "name": "ESA",
        "roles": [
          "producer",
          "processor",
          "licensor"
        ],
        "url": "https://earth.esa.int/web/guest/home"
      }
    ],
    "platform": "Sentinel-3A",
    "constellation": "Sentinel-3",
    "datetime": "2020-06-10T00:00:00Z"
  },
  "geometry": {
    "type": "Polygon",
    "coordinates": [
      [
        [
          -124.991,
          3.60956e-12
        ],
        [
          -121.045,
          3.60956e-12
        ],
        [
          -117.098,
          3.60956e-12
        ],
        [
          -113.152,
          3.60956e-12
        ],
        [
          -109.205,
          3.60956e-12
        ],
        [
          -105.259,
          3.60956e-12
        ],
        [
          -101.313,
          3.60956e-12
        ],
        [
          -97.3661,
          3.60956e-12
        ],
        [
          -93.4196,
          3.60956e-12
        ],
        [
          -89.4732,
          3.60956e-12
        ],
        [
          -85.5268,
          3.60956e-12
        ],
        [
          -81.5804,
          3.60956e-12
        ],
        [
          -77.6339,
          3.60956e-12
        ],
        [
          -73.6875,
          3.60956e-12
        ],
        [
          -69.7411,
          3.60956e-12
        ],
        [
          -65.7946,
          3.60956e-12
        ],
        [
          -61.8482,
          3.60956e-12
        ],
        [
          -57.9018,
          3.60956e-12
        ],
        [
          -53.9554,
          3.60956e-12
        ],
        [
          -50.0089,
          3.60956e-12
        ],
        [
          -50.0,
          3.60956e-12
        ],
        [
          -50.0,
          0.0982143
        ],
        [
          -50.0,
          0.491071
        ],
        [
          -50.0,
          0.883929
        ],
        [
          -50.0,
          1.27679
        ],
        [
          -50.0,
          1.66964
        ],
        [
          -50.0,
          2.0625
        ],
        [
          -50.0,
          2.45536
        ],
        [
          -50.0,
          2.84821
        ],
        [
          -50.0,
          3.24107
        ],
        [
          -50.0,
          3.63393
        ],
        [
          -50.0,
          4.02679
        ],
        [
          -50.0,
          4.41964
        ],
        [
          -50.0,
          4.8125
        ],
        [
          -50.0,
          5.20536
        ],
        [
          -50.0,
          5.59821
        ],
        [
          -50.0,
          5.99107
        ],
        [
          -50.0,
          6.38393
        ],
        [
          -50.0,
          6.77679
        ],
        [
          -50.0,
          7.16964
        ],
        [
          -50.0,
          7.5625
        ],
        [
          -50.0,
          7.95536
        ],
        [
          -50.0,
          8.34821
        ],
        [
          -50.0,
          8.74107
        ],
        [
          -50.0,
          9.13393
        ],
        [
          -50.0,
          9.52679
        ],
        [
          -50.0,
          9.91964
        ],
        [
          -50.0,
          10.3125
        ],
        [
          -50.0,
          10.7054
        ],
        [
          -50.0,
          11.0982
        ],
        [
          -50.0,
          11.4911
        ],
        [
          -50.0,
          11.8839
        ],
        [
          -50.0,
          12.2768
        ],
        [
          -50.0,
          12.6696
        ],
        [
          -50.0,
          13.0625
        ],
        [
          -50.0,
          13.4554
        ],
        [
          -50.0,
          13.8482
        ],
        [
          -50.0,
          14.2411
        ],
        [
          -50.0,
          14.6339
        ],
        [
          -50.0,
          15.0268
        ],
        [
          -50.0,
          15.4196
        ],
        [
          -50.0,
          15.8125
        ],
        [
          -50.0,
          16.2054
        ],
        [
          -50.0,
          16.5982
        ],
        [
          -50.0,
          16.9911
        ],
        [
          -50.0,
          17.3839
        ],
        [
          -50.0,
          17.7768
        ],
        [
          -50.0,
          18.1696
        ],
        [
          -50.0,
          18.5625
        ],
        [
          -50.0,
          18.9554
        ],
        [
          -50.0,
          19.3482
        ],
        [
          -50.0,
          19.7411
        ],
        [
          -50.0,
          20.1339
        ],
        [
          -50.0,
          20.5268
        ],
        [
          -50.0,
          20.9196
        ],
        [
          -50.0,
          21.3125
        ],
        [
          -50.0,
          21.7054
        ],
        [
          -50.0,
          22.0982
        ],
        [
          -50.0,
          22.4911
        ],
        [
          -50.0,
          22.8839
        ],
        [
          -50.0,
          23.2768
        ],
        [
          -50.0,
          23.6696
        ],
        [
          -50.0,
          24.0625
        ],
        [
          -50.0,
          24.4554
        ],
        [
          -50.0,
          24.8482
        ],
        [
          -50.0,
          25.2411
        ],
        [
          -50.0,
          25.6339
        ],
        [
          -50.0,
          26.0268
        ],
        [
          -50.0,
          26.4196
        ],
        [
          -50.0,
          26.8125
        ],
        [
          -50.0,
          27.2054
        ],
        [
          -50.0,
          27.5982
        ],
        [
          -50.0,
          27.9911
        ],
        [
          -50.0,
          28.3839
        ],
        [
          -50.0,
          28.7768
        ],
        [
          -50.0,
          29.1696
        ],
        [
          -50.0,
          29.5625
        ],
        [
          -50.0,
          29.9554
        ],
        [
          -50.0,
          30.3482
        ],
        [
          -50.0,
          30.7411
        ],
        [
          -50.0,
          31.1339
        ],
        [
          -50.0,
          31.5268
        ],
        [
          -50.0,
          31.9196
        ],
        [
          -50.0,
          32.3125
        ],
        [
          -50.0,
          32.7054
        ],
        [
          -50.0,
          33.0982
        ],
        [
          -50.0,
          33.4911
        ],
        [
          -50.0,
          33.8839
        ],
        [
          -50.0,
          34.2768
        ],
        [
          -50.0,
          34.6696
        ],
        [
          -50.0,
          35.0625
        ],
        [
          -50.0,
          35.4554
        ],
        [
          -50.0,
          35.8482
        ],
        [
          -50.0,
          36.2411
        ],
        [
          -50.0,
          36.6339
        ],
        [
          -50.0,
          37.0268
        ],
        [
          -50.0,
          37.4196
        ],
        [
          -50.0,
          37.8125
        ],
        [
          -50.0,
          38.2054
        ],
        [
          -50.0,
          38.5982
        ],
        [
          -50.0,
          38.9911
        ],
        [
          -50.0,
          39.3839
        ],
        [
          -50.0,
          39.7768
        ],
        [
          -50.0,
          40.1696
        ],
        [
          -50.0,
          40.5625
        ],
        [
          -50.0,
          40.9554
        ],
        [
          -50.0,
          41.3482
        ],
        [
          -50.0,
          41.7411
        ],
        [
          -50.0,
          42.1339
        ],
        [
          -50.0,
          42.5268
        ],
        [
          -50.0,
          42.9196
        ],
        [
          -50.0,
          43.3125
        ],
        [
          -50.0,
          43.7054
        ],
        [
          -50.0,
          44.0982
        ],
        [
          -50.0,
          44.4911
        ],
        [
          -50.0,
          44.8839
        ],
        [
          -50.0,
          45.2768
        ],
        [
          -50.0,
          45.6696
        ],
        [
          -50.0,
          46.0625
        ],
        [
          -50.0,
          46.4554
        ],
        [
          -50.0,
          46.8482
        ],
        [
          -50.0,
          47.2411
        ],
        [
          -50.0,
          47.6339
        ],
        [
          -50.0,
          48.0268
        ],
        [
          -50.0,
          48.4196
        ],
        [
          -50.0,
          48.8125
        ],
        [
          -50.0,
          49.2054
        ],
        [
          -50.0,
          49.5982
        ],
        [
          -50.0,
          49.9911
        ],
        [
          -50.0089,
          49.9911
        ],
        [
          -53.9554,
          49.9911
        ],
        [
          -57.9018,
          49.9911
        ],
        [
          -61.8482,
          49.9911
        ],
        [
          -65.7946,
          49.9911
        ],
        [
          -69.7411,
          49.9911
        ],
        [
          -73.6875,
          49.9911
        ],
        [
          -77.6339,
          49.9911
        ],
        [
          -81.5804,
          49.9911
        ],
        [
          -85.5268,
          49.9911
        ],
        [
          -89.4732,
          49.9911
        ],
        [
          -93.4196,
          49.9911
        ],
        [
          -97.3661,
          49.9911
        ],
        [
          -101.313,
          49.9911
        ],
        [
          -105.259,
          49.9911
        ],
        [
          -109.205,
          49.9911
        ],
        [
          -113.152,
          49.9911
        ],
        [
          -117.098,
          49.9911
        ],
        [
          -121.045,
          49.9911
        ],
        [
          -124.991,
          49.9911
        ],
        [
          -124.991,
          49.5982
        ],
        [
          -124.991,
          49.2054
        ],
        [
          -124.991,
          48.8125
        ],
        [
          -124.991,
          48.4196
        ],
        [
          -124.991,
          48.0268
        ],
        [
          -124.991,
          47.6339
        ],
        [
          -124.991,
          47.2411
        ],
        [
          -124.991,
          46.8482
        ],
        [
          -124.991,
          46.4554
        ],
        [
          -124.991,
          46.0625
        ],
        [
          -124.991,
          45.6696
        ],
        [
          -124.991,
          45.2768
        ],
        [
          -124.991,
          44.8839
        ],
        [
          -124.991,
          44.4911
        ],
        [
          -124.991,
          44.0982
        ],
        [
          -124.991,
          43.7054
        ],
        [
          -124.991,
          43.3125
        ],
        [
          -124.991,
          42.9196
        ],
        [
          -124.991,
          42.5268
        ],
        [
          -124.991,
          42.1339
        ],
        [
          -124.991,
          41.7411
        ],
        [
          -124.991,
          41.3482
        ],
        [
          -124.991,
          40.9554
        ],
        [
          -124.991,
          40.5625
        ],
        [
          -124.991,
          40.1696
        ],
        [
          -124.991,
          39.7768
        ],
        [
          -124.991,
          39.3839
        ],
        [
          -124.991,
          38.9911
        ],
        [
          -124.991,
          38.5982
        ],
        [
          -124.991,
          38.2054
        ],
        [
          -124.991,
          37.8125
        ],
        [
          -124.991,
          37.4196
        ],
        [
          -124.991,
          37.0268
        ],
        [
          -124.991,
          36.6339
        ],
        [
          -124.991,
          36.2411
        ],
        [
          -124.991,
          35.8482
        ],
        [
          -124.991,
          35.4554
        ],
        [
          -124.991,
          35.0625
        ],
        [
          -124.991,
          34.6696
        ],
        [
          -124.991,
          34.2768
        ],
        [
          -124.991,
          33.8839
        ],
        [
          -124.991,
          33.4911
        ],
        [
          -124.991,
          33.0982
        ],
        [
          -124.991,
          32.7054
        ],
        [
          -124.991,
          32.3125
        ],
        [
          -124.991,
          31.9196
        ],
        [
          -124.991,
          31.5268
        ],
        [
          -124.991,
          31.1339
        ],
        [
          -124.991,
          30.7411
        ],
        [
          -124.991,
          30.3482
        ],
        [
          -124.991,
          29.9554
        ],
        [
          -124.991,
          29.5625
        ],
        [
          -124.991,
          29.1696
        ],
        [
          -124.991,
          28.7768
        ],
        [
          -124.991,
          28.3839
        ],
        [
          -124.991,
          27.9911
        ],
        [
          -124.991,
          27.5982
        ],
        [
          -124.991,
          27.2054
        ],
        [
          -124.991,
          26.8125
        ],
        [
          -124.991,
          26.4196
        ],
        [
          -124.991,
          26.0268
        ],
        [
          -124.991,
          25.6339
        ],
        [
          -124.991,
          25.2411
        ],
        [
          -124.991,
          24.8482
        ],
        [
          -124.991,
          24.4554
        ],
        [
          -124.991,
          24.0625
        ],
        [
          -124.991,
          23.6696
        ],
        [
          -124.991,
          23.2768
        ],
        [
          -124.991,
          22.8839
        ],
        [
          -124.991,
          22.4911
        ],
        [
          -124.991,
          22.0982
        ],
        [
          -124.991,
          21.7054
        ],
        [
          -124.991,
          21.3125
        ],
        [
          -124.991,
          20.9196
        ],
        [
          -124.991,
          20.5268
        ],
        [
          -124.991,
          20.1339
        ],
        [
          -124.991,
          19.7411
        ],
        [
          -124.991,
          19.3482
        ],
        [
          -124.991,
          18.9554
        ],
        [
          -124.991,
          18.5625
        ],
        [
          -124.991,
          18.1696
        ],
        [
          -124.991,
          17.7768
        ],
        [
          -124.991,
          17.3839
        ],
        [
          -124.991,
          16.9911
        ],
        [
          -124.991,
          16.5982
        ],
        [
          -124.991,
          16.2054
        ],
        [
          -124.991,
          15.8125
        ],
        [
          -124.991,
          15.4196
        ],
        [
          -124.991,
          15.0268
        ],
        [
          -124.991,
          14.6339
        ],
        [
          -124.991,
          14.2411
        ],
        [
          -124.991,
          13.8482
        ],
        [
          -124.991,
          13.4554
        ],
        [
          -124.991,
          13.0625
        ],
        [
          -124.991,
          12.6696
        ],
        [
          -124.991,
          12.2768
        ],
        [
          -124.991,
          11.8839
        ],
        [
          -124.991,
          11.4911
        ],
        [
          -124.991,
          11.0982
        ],
        [
          -124.991,
          10.7054
        ],
        [
          -124.991,
          10.3125
        ],
        [
          -124.991,
          9.91964
        ],
        [
          -124.991,
          9.52679
        ],
        [
          -124.991,
          9.13393
        ],
        [
          -124.991,
          8.74107
        ],
        [
          -124.991,
          8.34821
        ],
        [
          -124.991,
          7.95536
        ],
        [
          -124.991,
          7.5625
        ],
        [
          -124.991,
          7.16964
        ],
        [
          -124.991,
          6.77679
        ],
        [
          -124.991,
          6.38393
        ],
        [
          -124.991,
          5.99107
        ],
        [
          -124.991,
          5.59821
        ],
        [
          -124.991,
          5.20536
        ],
        [
          -124.991,
          4.8125
        ],
        [
          -124.991,
          4.41964
        ],
        [
          -124.991,
          4.02679
        ],
        [
          -124.991,
          3.63393
        ],
        [
          -124.991,
          3.24107
        ],
        [
          -124.991,
          2.84821
        ],
        [
          -124.991,
          2.45536
        ],
        [
          -124.991,
          2.0625
        ],
        [
          -124.991,
          1.66964
        ],
        [
          -124.991,
          1.27679
        ],
        [
          -124.991,
          0.883929
        ],
        [
          -124.991,
          0.491071
        ],
        [
          -124.991,
          0.0982143
        ],
        [
          -124.991,
          3.60956e-12
        ]
      ]
    ]
  },
  "links": [
    {
      "rel": "self",
      "href": "/opt/stactools-sentinel3/examples/S3A_SY_2_VG1____20200609T120000_20200610T120000_20200615T121610_CENTRAL_AMERICA___LN2_O_NT_002.json",
      "type": "application/json"
    }
  ],
  "assets": {
    "safe-manifest": {
      "href": "/opt/stactools-sentinel3/tests/data-files/S3A_SY_2_VG1____20200609T120000_20200610T120000_20200615T121610_CENTRAL_AMERICA___LN2_O_NT_002.SEN3/xfdumanifest.xml",
      "type": "application/xml",
      "roles": [
        "metadata"
      ]
    },
    "b0Data": {
      "href": "/opt/stactools-sentinel3/tests/data-files/S3A_SY_2_VG1____20200609T120000_20200610T120000_20200615T121610_CENTRAL_AMERICA___LN2_O_NT_002.SEN3/B0.nc",
      "type": "application/x-netcdf",
      "description": "Surface Reflectance Data Set associated with VGT-B0 channel",
      "eo:bands": [
        {
          "name": "B0",
          "description": "OLCI channels Oa02, Oa03",
          "center_wavelength": 450,
          "band_width": 20
        }
      ],
      "roles": [
        "data"
      ]
    },
    "b2Data": {
      "href": "/opt/stactools-sentinel3/tests/data-files/S3A_SY_2_VG1____20200609T120000_20200610T120000_20200615T121610_CENTRAL_AMERICA___LN2_O_NT_002.SEN3/B2.nc",
      "type": "application/x-netcdf",
      "description": "Surface Reflectance Data Set associated with VGT-B2 channel",
      "eo:bands": [
        {
          "name": "B2",
          "description": "OLCI channels Oa06, Oa07, Oa08, Oa09, Oa10",
          "center_wavelength": 645,
          "band_width": 35
        }
      ],
      "roles": [
        "data"
      ]
    },
    "b3Data": {
      "href": "/opt/stactools-sentinel3/tests/data-files/S3A_SY_2_VG1____20200609T120000_20200610T120000_20200615T121610_CENTRAL_AMERICA___LN2_O_NT_002.SEN3/B3.nc",
      "type": "application/x-netcdf",
      "description": "Surface Reflectance Data Set associated with VGT-B3 channel",
      "eo:bands": [
        {
          "name": "B3",
          "description": "OLCI channels Oa16, Oa17, Oa18, Oa21",
          "center_wavelength": 835,
          "band_width": 55
        }
      ],
      "roles": [
        "data"
      ]
    },
    "mirData": {
      "href": "/opt/stactools-sentinel3/tests/data-files/S3A_SY_2_VG1____20200609T120000_20200610T120000_20200615T121610_CENTRAL_AMERICA___LN2_O_NT_002.SEN3/MIR.nc",
      "type": "application/x-netcdf",
      "description": "Surface Reflectance Data Set associated with VGT-MIR channel",
      "eo:bands": [
        {
          "name": "MIR",
          "description": "SLSTR nadir and oblique channels S5, S6",
          "center_wavelength": 1665,
          "band_width": 85
        }
      ],
      "roles": [
        "data"
      ]
    },
    "ndviData": {
      "href": "/opt/stactools-sentinel3/tests/data-files/S3A_SY_2_VG1____20200609T120000_20200610T120000_20200615T121610_CENTRAL_AMERICA___LN2_O_NT_002.SEN3/NDVI.nc",
      "type": "application/x-netcdf",
      "description": "Normalised difference vegetation index",
      "eo:bands": [
        {
          "name": "B2",
          "description": "OLCI channels Oa06, Oa07, Oa08, Oa09, Oa10",
          "center_wavelength": 645,
          "band_width": 35
        },
        {
          "name": "B3",
          "description": "OLCI channels Oa16, Oa17, Oa18, Oa21",
          "center_wavelength": 835,
          "band_width": 55
        }
      ],
      "roles": [
        "data"
      ]
    },
    "vaaData": {
      "href": "/opt/stactools-sentinel3/tests/data-files/S3A_SY_2_VG1____20200609T120000_20200610T120000_20200615T121610_CENTRAL_AMERICA___LN2_O_NT_002.SEN3/vaa.nc",
      "type": "application/x-netcdf",
      "description": "View azimuth angle data",
      "roles": [
        "data"
      ]
    },
    "vzaData": {
      "href": "/opt/stactools-sentinel3/tests/data-files/S3A_SY_2_VG1____20200609T120000_20200610T120000_20200615T121610_CENTRAL_AMERICA___LN2_O_NT_002.SEN3/vza.nc",
      "type": "application/x-netcdf",
      "description": "View zenith angle data",
      "roles": [
        "data"
      ]
    },
    "saaData": {
      "href": "/opt/stactools-sentinel3/tests/data-files/S3A_SY_2_VG1____20200609T120000_20200610T120000_20200615T121610_CENTRAL_AMERICA___LN2_O_NT_002.SEN3/saa.nc",
      "type": "application/x-netcdf",
      "description": "Solar azimuth angle data",
      "roles": [
        "data"
      ]
    },
    "szaData": {
      "href": "/opt/stactools-sentinel3/tests/data-files/S3A_SY_2_VG1____20200609T120000_20200610T120000_20200615T121610_CENTRAL_AMERICA___LN2_O_NT_002.SEN3/sza.nc",
      "type": "application/x-netcdf",
      "description": "Solar zenith angle data",
      "roles": [
        "data"
      ]
    },
    "agData": {
      "href": "/opt/stactools-sentinel3/tests/data-files/S3A_SY_2_VG1____20200609T120000_20200610T120000_20200615T121610_CENTRAL_AMERICA___LN2_O_NT_002.SEN3/ag.nc",
      "type": "application/x-netcdf",
      "description": "Aerosol optical thickness data",
      "roles": [
        "data"
      ]
    },
    "ogData": {
      "href": "/opt/stactools-sentinel3/tests/data-files/S3A_SY_2_VG1____20200609T120000_20200610T120000_20200615T121610_CENTRAL_AMERICA___LN2_O_NT_002.SEN3/og.nc",
      "type": "application/x-netcdf",
      "description": "Total Ozone column data",
      "roles": [
        "data"
      ]
    },
    "wvgData": {
      "href": "/opt/stactools-sentinel3/tests/data-files/S3A_SY_2_VG1____20200609T120000_20200610T120000_20200615T121610_CENTRAL_AMERICA___LN2_O_NT_002.SEN3/wvg.nc",
      "type": "application/x-netcdf",
      "description": "Total column Water vapour data",
      "roles": [
        "data"
      ]
    },
    "tgData": {
      "href": "/opt/stactools-sentinel3/tests/data-files/S3A_SY_2_VG1____20200609T120000_20200610T120000_20200615T121610_CENTRAL_AMERICA___LN2_O_NT_002.SEN3/tg.nc",
      "type": "application/x-netcdf",
      "description": "Synthesis time data",
      "roles": [
        "data"
      ]
    },
    "smData": {
      "href": "/opt/stactools-sentinel3/tests/data-files/S3A_SY_2_VG1____20200609T120000_20200610T120000_20200615T121610_CENTRAL_AMERICA___LN2_O_NT_002.SEN3/sm.nc",
      "type": "application/x-netcdf",
      "description": "Status Map data",
      "roles": [
        "data"
      ]
    }
  },
  "bbox": [
    -124.991,
    3.60956e-12,
    -50.0,
    49.9911
  ],
  "stac_extensions": [
    "https://stac-extensions.github.io/sat/v1.0.0/schema.json",
    "https://stac-extensions.github.io/eo/v1.0.0/schema.json",
    "https://stac-extensions.github.io/projection/v1.0.0/schema.json"
  ]
}